{"name": "Is the middle petal divided by a central line?", "slug": "divided_line", "children": [{"name": "Are the three horizontal bars in the center all the same width?", "slug": "hoz_bars_equal", "children": [{"name": "Fleur-de-lis B.d.", "slug": "Bd"}, {"name": "Fleur-de-lis B.a.", "slug": "Ba"}]}, {"name": "Do the petals form vertical lines where they join together at their base?", "slug": "vertical_lines", "children": [{"name": "Are the corners of the bars at the center rounded?", "slug": "corners_rounded", "children": [{"name": "Does the outer tip of one of the small leaves brush the chainline?", "slug": "leaves_touch_chainline", "children": [{"name": "Fleur-de-lis C.a.", "slug": "Ca"}, {"name": "Fleur-de-lis C.b.", "slug": "Cb"}]}, {"name": "Fleur-de-lis C.b.", "slug": "Cc"}]}, {"name": "Fleur-de-lis A.a.", "slug": "Aa"}]}]}